MANIFEST.in
README.md
requirements.txt
setup.py
hrpc/__init__.py
hrpc/client.py
hrpc/exceptions.py
hrpc/object_proxy.py
hrpc.egg-info/PKG-INFO
hrpc.egg-info/SOURCES.txt
hrpc.egg-info/dependency_links.txt
hrpc.egg-info/requires.txt
hrpc.egg-info/top_level.txt
hrpc/transport/__init__.py
hrpc/transport/http.py
hrpc/utils/__init__.py
hrpc/utils/promise.py
test/__init__.py
test/test_http_transport.py