Metadata-Version: 1.0
Name: hrpc
Version: 1.0.4
Summary: A common interface based RPC framework
Home-page: https://github.com/AirtestProject/hrpc
Author: UNKNOWN
Author-email: UNKNOWN
License: Apache License 2.0
Keywords: hrpc rpc
Platform: UNKNOWN
